[{"id":"1762885356906ea74667fe09ba","name":"NICOLA LANGELLA","phone":"3468015388","createdAt":"2025-11-11T18:22:36.906Z","updatedAt":"2025-11-11T18:22:36.906Z","activated":["pacchi"],"acceptance":false,"fromPacchi":true,"done":false,"reminders":[{"type":"energia","dueAt":"2025-11-17T18:22:36.906Z","sent":false,"sentAt":null},{"type":"sim","dueAt":"2025-11-24T18:22:36.906Z","sent":false,"sentAt":null},{"type":"fissomobile","dueAt":"2025-12-02T18:22:36.906Z","sent":false,"sentAt":null},{"type":"rate","dueAt":"2025-12-11T18:22:36.906Z","sent":false,"sentAt":null}],"remindersCycle":1,"responded":false},{"id":"17628850231706ccd971379e768","name":"FLAVIA STABILE","phone":"3392891202","createdAt":"2025-11-11T18:17:03.170Z","updatedAt":"2025-11-11T18:17:03.170Z","activated":["pacchi"],"acceptance":false,"fromPacchi":true,"done":false,"reminders":[{"type":"rate","dueAt":"2025-11-17T18:17:03.170Z","sent":false,"sentAt":null},{"type":"energia","dueAt":"2025-11-24T18:17:03.170Z","sent":false,"sentAt":null},{"type":"sim","dueAt":"2025-12-02T18:17:03.170Z","sent":false,"sentAt":null},{"type":"fissomobile","dueAt":"2025-12-11T18:17:03.170Z","sent":false,"sentAt":null}],"remindersCycle":1,"responded":false},{"id":"17628843036262c06d82a10a3d8","name":"GIOVANNI DEL PRETE","phone":"3479088803","createdAt":"2025-11-11T18:05:03.626Z","updatedAt":"2025-11-11T18:05:03.626Z","activated":["sim"],"acceptance":false,"fromPacchi":false,"done":false,"reminders":[{"type":"rate","dueAt":"2025-11-17T18:05:03.626Z","sent":false,"sentAt":null},{"type":"energia","dueAt":"2025-11-24T18:05:03.626Z","sent":false,"sentAt":null},{"type":"fissomobile","dueAt":"2025-12-02T18:05:03.626Z","sent":false,"sentAt":null}],"remindersCycle":1,"responded":false},{"id":"17628840542455b2c7832810a4","name":"SARA ANGELLOTTI","phone":"3510144764","createdAt":"2025-11-11T18:00:54.245Z","updatedAt":"2025-11-11T18:00:54.245Z","activated":["pacchi"],"acceptance":false,"fromPacchi":true,"done":false,"reminders":[{"type":"sim","dueAt":"2025-11-17T17:59:05.421Z","sent":false,"sentAt":null},{"type":"energia","dueAt":"2025-11-24T17:59:05.421Z","sent":false,"sentAt":null},{"type":"fissomobile","dueAt":"2025-12-02T17:59:05.421Z","sent":false,"sentAt":null},{"type":"rate","dueAt":"2025-12-11T17:59:05.421Z","sent":false,"sentAt":null}],"remindersCycle":1,"responded":false},{"id":"17628824685355c16ff107e2b","name":"DAVIDE DE STEFANO","phone":"3280878888","createdAt":"2025-11-11T17:34:28.535Z","updatedAt":"2025-11-11T17:34:28.535Z","activated":["pacchi"],"acceptance":false,"fromPacchi":true,"done":false,"reminders":[{"type":"sim","dueAt":"2025-11-17T17:34:28.535Z","sent":false,"sentAt":null},{"type":"rate","dueAt":"2025-11-24T17:34:28.535Z","sent":false,"sentAt":null},{"type":"energia","dueAt":"2025-12-02T17:34:28.535Z","sent":false,"sentAt":null},{"type":"fissomobile","dueAt":"2025-12-11T17:34:28.535Z","sent":false,"sentAt":null}],"remindersCycle":1,"responded":false},{"id":"1762881857013d245006397201","name":"ARCONE MARIO","phone":"3476677402","createdAt":"2025-11-11T17:24:17.013Z","updatedAt":"2025-11-11T17:24:17.013Z","activated":["pacchi"],"acceptance":false,"fromPacchi":true,"done":false,"reminders":[{"type":"sim","dueAt":"2025-11-17T17:24:17.013Z","sent":false,"sentAt":null},{"type":"rate","dueAt":"2025-11-24T17:24:17.013Z","sent":false,"sentAt":null},{"type":"energia","dueAt":"2025-12-02T17:24:17.013Z","sent":false,"sentAt":null},{"type":"fissomobile","dueAt":"2025-12-11T17:24:17.013Z","sent":false,"sentAt":null}],"remindersCycle":1,"responded":false},{"id":"17628816681323570888f0afe68","name":"CORCIONE LUCA","phone":"3393358434","createdAt":"2025-11-11T17:21:08.132Z","updatedAt":"2025-11-11T17:21:08.132Z","activated":["pacchi"],"acceptance":false,"fromPacchi":true,"done":false,"reminders":[{"type":"fissomobile","dueAt":"2025-11-17T17:21:08.132Z","sent":false,"sentAt":null},{"type":"energia","dueAt":"2025-11-24T17:21:08.132Z","sent":false,"sentAt":null},{"type":"rate","dueAt":"2025-12-02T17:21:08.132Z","sent":false,"sentAt":null},{"type":"sim","dueAt":"2025-12-11T17:21:08.132Z","sent":false,"sentAt":null}],"remindersCycle":1,"responded":false},{"id":"1762879386987182b99979b372","name":"ALESSANDRO IASCONE","phone":"3335353373","createdAt":"2025-11-11T16:43:06.987Z","updatedAt":"2025-11-11T16:43:06.988Z","activated":["pacchi"],"acceptance":false,"fromPacchi":true,"done":false,"reminders":[{"type":"rate","dueAt":"2025-11-17T16:43:06.987Z","sent":false,"sentAt":null},{"type":"energia","dueAt":"2025-11-24T16:43:06.987Z","sent":false,"sentAt":null},{"type":"fissomobile","dueAt":"2025-12-02T16:43:06.987Z","sent":false,"sentAt":null},{"type":"sim","dueAt":"2025-12-11T16:43:06.987Z","sent":false,"sentAt":null}],"remindersCycle":1,"responded":false},{"id":"1762879315470690ce7f740d56","name":"ROSARIA COSITORE","phone":"3807511511","createdAt":"2025-11-11T16:41:55.470Z","updatedAt":"2025-11-11T16:41:55.471Z","activated":["pacchi"],"acceptance":false,"fromPacchi":true,"done":false,"reminders":[{"type":"fissomobile","dueAt":"2025-11-17T16:41:55.470Z","sent":false,"sentAt":null},{"type":"energia","dueAt":"2025-11-24T16:41:55.470Z","sent":false,"sentAt":null},{"type":"rate","dueAt":"2025-12-02T16:41:55.470Z","sent":false,"sentAt":null},{"type":"sim","dueAt":"2025-12-11T16:41:55.470Z","sent":false,"sentAt":null}],"remindersCycle":1,"responded":false},{"id":"1762879219926c1e38e827ad3a8","name":"GIUSEPPE MORRA","phone":"3388700148","createdAt":"2025-11-11T16:40:19.926Z","updatedAt":"2025-11-11T16:40:19.926Z","activated":["pacchi"],"acceptance":false,"fromPacchi":true,"done":false,"reminders":[{"type":"sim","dueAt":"2025-11-17T16:40:19.926Z","sent":false,"sentAt":null},{"type":"energia","dueAt":"2025-11-24T16:40:19.926Z","sent":false,"sentAt":null},{"type":"fissomobile","dueAt":"2025-12-02T16:40:19.926Z","sent":false,"sentAt":null},{"type":"rate","dueAt":"2025-12-11T16:40:19.926Z","sent":false,"sentAt":null}],"remindersCycle":1,"responded":false},{"id":"17628789994309b6061fa614648","name":"SALVATORE TOPO","phone":"3355282307","createdAt":"2025-11-11T16:36:39.430Z","updatedAt":"2025-11-11T16:36:39.430Z","activated":["pacchi"],"acceptance":false,"fromPacchi":true,"done":false,"reminders":[{"type":"energia","dueAt":"2025-11-17T16:36:39.430Z","sent":false,"sentAt":null},{"type":"fissomobile","dueAt":"2025-11-24T16:36:39.430Z","sent":false,"sentAt":null},{"type":"sim","dueAt":"2025-12-02T16:36:39.430Z","sent":false,"sentAt":null},{"type":"rate","dueAt":"2025-12-11T16:36:39.430Z","sent":false,"sentAt":null}],"remindersCycle":1,"responded":false},{"id":"176287880409462c01fb84c263","name":"MARTA BAIANO","phone":"3662217444","createdAt":"2025-11-11T16:33:24.094Z","updatedAt":"2025-11-11T16:33:24.094Z","activated":["pacchi"],"acceptance":false,"fromPacchi":true,"done":false,"reminders":[{"type":"sim","dueAt":"2025-11-17T16:33:24.094Z","sent":false,"sentAt":null},{"type":"energia","dueAt":"2025-11-24T16:33:24.094Z","sent":false,"sentAt":null},{"type":"rate","dueAt":"2025-12-02T16:33:24.094Z","sent":false,"sentAt":null},{"type":"fissomobile","dueAt":"2025-12-11T16:33:24.094Z","sent":false,"sentAt":null}],"remindersCycle":1,"responded":false},{"id":"1762878242005b9434a5151ab7","name":"MARIA DI MAIO","phone":"3389129876","createdAt":"2025-11-11T16:24:02.005Z","updatedAt":"2025-11-11T16:24:02.006Z","activated":["pacchi"],"acceptance":false,"fromPacchi":true,"done":false,"reminders":[{"type":"sim","dueAt":"2025-11-17T16:24:02.005Z","sent":false,"sentAt":null},{"type":"energia","dueAt":"2025-11-24T16:24:02.005Z","sent":false,"sentAt":null},{"type":"rate","dueAt":"2025-12-02T16:24:02.005Z","sent":false,"sentAt":null},{"type":"fissomobile","dueAt":"2025-12-11T16:24:02.005Z","sent":false,"sentAt":null}],"remindersCycle":1,"responded":false},{"id":"1762876636885c166e34c05bf","name":"LOREDANA PANELLA","phone":"3396084979","createdAt":"2025-11-11T15:57:16.885Z","updatedAt":"2025-11-11T15:57:16.885Z","activated":["pacchi"],"acceptance":false,"fromPacchi":true,"done":false,"reminders":[{"type":"energia","dueAt":"2025-11-17T15:57:16.885Z","sent":false,"sentAt":null},{"type":"sim","dueAt":"2025-11-24T15:57:16.885Z","sent":false,"sentAt":null},{"type":"rate","dueAt":"2025-12-02T15:57:16.885Z","sent":false,"sentAt":null},{"type":"fissomobile","dueAt":"2025-12-11T15:57:16.885Z","sent":false,"sentAt":null}],"remindersCycle":1,"responded":false},{"id":"176287640088407652687ed2f6","name":"LORENZO GROSSI","phone":"3342588130","createdAt":"2025-11-11T15:53:20.884Z","updatedAt":"2025-11-11T15:53:20.884Z","activated":["pacchi"],"acceptance":false,"fromPacchi":true,"done":false,"reminders":[{"type":"rate","dueAt":"2025-11-17T15:53:20.884Z","sent":false,"sentAt":null},{"type":"energia","dueAt":"2025-11-24T15:53:20.884Z","sent":false,"sentAt":null},{"type":"fissomobile","dueAt":"2025-12-02T15:53:20.884Z","sent":false,"sentAt":null},{"type":"sim","dueAt":"2025-12-11T15:53:20.884Z","sent":false,"sentAt":null}],"remindersCycle":1,"responded":false},{"id":"1762876286285c46e1bd5842d58","name":"ALESSIA MILUCCI","phone":"3313044029","createdAt":"2025-11-11T15:51:26.285Z","updatedAt":"2025-11-11T15:51:26.285Z","activated":["pacchi"],"acceptance":false,"fromPacchi":true,"done":false,"reminders":[{"type":"energia","dueAt":"2025-11-17T15:51:26.285Z","sent":false,"sentAt":null},{"type":"rate","dueAt":"2025-11-24T15:51:26.285Z","sent":false,"sentAt":null},{"type":"sim","dueAt":"2025-12-02T15:51:26.285Z","sent":false,"sentAt":null},{"type":"fissomobile","dueAt":"2025-12-11T15:51:26.285Z","sent":false,"sentAt":null}],"remindersCycle":1,"responded":false},{"id":"17628758280126afb98e5e2edd","name":"GIANNI COZZUTO","phone":"3517836259","createdAt":"2025-11-11T15:43:48.012Z","updatedAt":"2025-11-11T15:43:48.013Z","activated":["pacchi"],"acceptance":false,"fromPacchi":true,"done":false,"reminders":[{"type":"sim","dueAt":"2025-11-17T15:43:48.012Z","sent":false,"sentAt":null},{"type":"rate","dueAt":"2025-11-24T15:43:48.012Z","sent":false,"sentAt":null},{"type":"energia","dueAt":"2025-12-02T15:43:48.012Z","sent":false,"sentAt":null},{"type":"fissomobile","dueAt":"2025-12-11T15:43:48.012Z","sent":false,"sentAt":null}],"remindersCycle":1,"responded":false},{"id":"176287547150008b6e18a1f8cb","name":"Christian Garofalo","phone":"3511262985","createdAt":"2025-11-11T15:37:51.500Z","updatedAt":"2025-11-11T15:37:51.501Z","activated":["pacchi"],"acceptance":false,"fromPacchi":true,"done":false,"reminders":[{"type":"fissomobile","dueAt":"2025-11-17T15:37:51.500Z","sent":false,"sentAt":null},{"type":"energia","dueAt":"2025-11-24T15:37:51.500Z","sent":false,"sentAt":null},{"type":"sim","dueAt":"2025-12-02T15:37:51.500Z","sent":false,"sentAt":null},{"type":"rate","dueAt":"2025-12-11T15:37:51.500Z","sent":false,"sentAt":null}],"remindersCycle":1,"responded":false},{"id":"1762874567812cc22137f030c","name":"MICHELE MURANO","phone":"3283389166","createdAt":"2025-11-11T15:22:47.812Z","updatedAt":"2025-11-11T15:22:47.812Z","activated":["pacchi"],"acceptance":false,"fromPacchi":true,"done":false,"reminders":[{"type":"fissomobile","dueAt":"2025-11-17T15:22:47.812Z","sent":false,"sentAt":null},{"type":"sim","dueAt":"2025-11-24T15:22:47.812Z","sent":false,"sentAt":null},{"type":"energia","dueAt":"2025-12-02T15:22:47.812Z","sent":false,"sentAt":null},{"type":"rate","dueAt":"2025-12-11T15:22:47.812Z","sent":false,"sentAt":null}],"remindersCycle":1,"responded":false}]